{
  "metadata": {
    "date_maj": "2025-11-13T11:16:39.838662",
    "timestamp": 1763032599,
    "nombre_actions": 47,
    "source": "BRVM",
    "version": "ultra_robuste",
    "statut": "succès",
    "environment": "github_actions"
  },
  "data": [
    {
      "symbole": "ABJC",
      "nom": "SERVAIR ABIDJAN COTE D'IVOIRE",
      "dernier": 2380.0,
      "variation": 1.71,
      "ouverture": 2340.0,
      "haut": 2380.0,
      "bas": 2380.0,
      "volume": 1291,
      "veille": 2340.0,
      "date_maj": "2025-11-13T11:16:39.830508"
    },
    {
      "symbole": "BICB",
      "nom": "BANQUE INTERNATIONALE POUR L’INDUSTRIE ET LE COMMERCE DU BENIN",
      "dernier": 5000.0,
      "variation": 0.0,
      "ouverture": 5000.0,
      "haut": 5000.0,
      "bas": 5000.0,
      "volume": 407,
      "veille": 5000.0,
      "date_maj": "2025-11-13T11:16:39.830662"
    },
    {
      "symbole": "BICC",
      "nom": "BICI COTE D'IVOIRE",
      "dernier": 19650.0,
      "variation": 0.77,
      "ouverture": 19650.0,
      "haut": 19650.0,
      "bas": 19650.0,
      "volume": 49,
      "veille": 19500.0,
      "date_maj": "2025-11-13T11:16:39.830762"
    },
    {
      "symbole": "BNBC",
      "nom": "BERNABE COTE D'IVOIRE",
      "dernier": 1500.0,
      "variation": 6.38,
      "ouverture": 1500.0,
      "haut": 1500.0,
      "bas": 1500.0,
      "volume": 880,
      "veille": 1420.0,
      "date_maj": "2025-11-13T11:16:39.830858"
    },
    {
      "symbole": "BOAB",
      "nom": "BANK OF AFRICA BENIN",
      "dernier": 5130.0,
      "variation": -1.16,
      "ouverture": 5100.0,
      "haut": 5130.0,
      "bas": 5130.0,
      "volume": 743,
      "veille": 5190.0,
      "date_maj": "2025-11-13T11:16:39.831035"
    },
    {
      "symbole": "BOABF",
      "nom": "BANK OF AFRICA BURKINA FASO",
      "dernier": 3550.0,
      "variation": 0.0,
      "ouverture": 3550.0,
      "haut": 3550.0,
      "bas": 3550.0,
      "volume": 4577,
      "veille": 3550.0,
      "date_maj": "2025-11-13T11:16:39.831196"
    },
    {
      "symbole": "BOAC",
      "nom": "BANK OF AFRICA COTE D'IVOIRE",
      "dernier": 7280.0,
      "variation": 1.39,
      "ouverture": 7180.0,
      "haut": 7280.0,
      "bas": 7280.0,
      "volume": 988,
      "veille": 7180.0,
      "date_maj": "2025-11-13T11:16:39.831329"
    },
    {
      "symbole": "BOAM",
      "nom": "BANK OF AFRICA MALI",
      "dernier": 3825.0,
      "variation": 0.0,
      "ouverture": 3825.0,
      "haut": 3825.0,
      "bas": 3825.0,
      "volume": 780,
      "veille": 3825.0,
      "date_maj": "2025-11-13T11:16:39.831437"
    },
    {
      "symbole": "BOAN",
      "nom": "BANK OF AFRICA NIGER",
      "dernier": 2500.0,
      "variation": -1.77,
      "ouverture": 2510.0,
      "haut": 2500.0,
      "bas": 2500.0,
      "volume": 1238,
      "veille": 2545.0,
      "date_maj": "2025-11-13T11:16:39.831528"
    },
    {
      "symbole": "BOAS",
      "nom": "BANK OF AFRICA SENEGAL",
      "dernier": 5300.0,
      "variation": 0.0,
      "ouverture": 5200.0,
      "haut": 5300.0,
      "bas": 5300.0,
      "volume": 2999,
      "veille": 5300.0,
      "date_maj": "2025-11-13T11:16:39.831665"
    },
    {
      "symbole": "CABC",
      "nom": "SICABLE COTE D'IVOIRE",
      "dernier": 2540.0,
      "variation": 0.0,
      "ouverture": 2540.0,
      "haut": 2540.0,
      "bas": 2540.0,
      "volume": 1346,
      "veille": 2540.0,
      "date_maj": "2025-11-13T11:16:39.831830"
    },
    {
      "symbole": "CBIBF",
      "nom": "CORIS BANK INTERNATIONAL BURKINA FASO",
      "dernier": 9985.0,
      "variation": 0.0,
      "ouverture": 0.0,
      "haut": 9985.0,
      "bas": 9985.0,
      "volume": 0,
      "veille": 9985.0,
      "date_maj": "2025-11-13T11:16:39.831986"
    },
    {
      "symbole": "CFAC",
      "nom": "CFAO MOTORS COTE D'IVOIRE",
      "dernier": 1610.0,
      "variation": -1.83,
      "ouverture": 1690.0,
      "haut": 1610.0,
      "bas": 1610.0,
      "volume": 5363,
      "veille": 1640.0,
      "date_maj": "2025-11-13T11:16:39.832186"
    },
    {
      "symbole": "CIEC",
      "nom": "CIE COTE D'IVOIRE",
      "dernier": 2620.0,
      "variation": 0.77,
      "ouverture": 2615.0,
      "haut": 2620.0,
      "bas": 2620.0,
      "volume": 3269,
      "veille": 2600.0,
      "date_maj": "2025-11-13T11:16:39.832343"
    },
    {
      "symbole": "ECOC",
      "nom": "ECOBANK COTE D'IVOIRE",
      "dernier": 15210.0,
      "variation": 0.07,
      "ouverture": 15740.0,
      "haut": 15210.0,
      "bas": 15210.0,
      "volume": 618,
      "veille": 15210.0,
      "date_maj": "2025-11-13T11:16:39.832475"
    },
    {
      "symbole": "ETIT",
      "nom": "Ecobank Transnational Incorporated TOGO",
      "dernier": 22.0,
      "variation": 0.0,
      "ouverture": 23.0,
      "haut": 22.0,
      "bas": 22.0,
      "volume": 283782,
      "veille": 22.0,
      "date_maj": "2025-11-13T11:16:39.832656"
    },
    {
      "symbole": "FTSC",
      "nom": "FILTISAC COTE D'IVOIRE",
      "dernier": 2450.0,
      "variation": -2.0,
      "ouverture": 2595.0,
      "haut": 2450.0,
      "bas": 2450.0,
      "volume": 996,
      "veille": 2500.0,
      "date_maj": "2025-11-13T11:16:39.832816"
    },
    {
      "symbole": "LNBB",
      "nom": "LOTERIE NATIONALE DU BENIN",
      "dernier": 3900.0,
      "variation": 0.13,
      "ouverture": 4000.0,
      "haut": 3900.0,
      "bas": 3900.0,
      "volume": 106,
      "veille": 3895.0,
      "date_maj": "2025-11-13T11:16:39.833001"
    },
    {
      "symbole": "NEIC",
      "nom": "NEI-CEDA COTE D'IVOIRE",
      "dernier": 985.0,
      "variation": 3.68,
      "ouverture": 930.0,
      "haut": 985.0,
      "bas": 985.0,
      "volume": 1997,
      "veille": 950.0,
      "date_maj": "2025-11-13T11:16:39.833234"
    },
    {
      "symbole": "NSBC",
      "nom": "NSIA BANQUE COTE D'IVOIRE",
      "dernier": 11830.0,
      "variation": 0.08,
      "ouverture": 11850.0,
      "haut": 11830.0,
      "bas": 11830.0,
      "volume": 1161,
      "veille": 11820.0,
      "date_maj": "2025-11-13T11:16:39.833388"
    },
    {
      "symbole": "NTLC",
      "nom": "NESTLE COTE D'IVOIRE",
      "dernier": 11500.0,
      "variation": 0.04,
      "ouverture": 11100.0,
      "haut": 11500.0,
      "bas": 11500.0,
      "volume": 222,
      "veille": 11495.0,
      "date_maj": "2025-11-13T11:16:39.833587"
    },
    {
      "symbole": "ONTBF",
      "nom": "ONATEL BURKINA FASO",
      "dernier": 2405.0,
      "variation": 0.21,
      "ouverture": 2495.0,
      "haut": 2405.0,
      "bas": 2405.0,
      "volume": 172,
      "veille": 2405.0,
      "date_maj": "2025-11-13T11:16:39.833748"
    },
    {
      "symbole": "ORAC",
      "nom": "ORANGE COTE D'IVOIRE",
      "dernier": 14280.0,
      "variation": -1.86,
      "ouverture": 14500.0,
      "haut": 14280.0,
      "bas": 14280.0,
      "volume": 682,
      "veille": 14550.0,
      "date_maj": "2025-11-13T11:16:39.833870"
    },
    {
      "symbole": "ORGT",
      "nom": "ORAGROUP TOGO",
      "dernier": 2550.0,
      "variation": 0.0,
      "ouverture": 2640.0,
      "haut": 2550.0,
      "bas": 2550.0,
      "volume": 315,
      "veille": 2550.0,
      "date_maj": "2025-11-13T11:16:39.834037"
    },
    {
      "symbole": "PALC",
      "nom": "PALM COTE D'IVOIRE",
      "dernier": 8150.0,
      "variation": -0.61,
      "ouverture": 8200.0,
      "haut": 8150.0,
      "bas": 8150.0,
      "volume": 413,
      "veille": 8200.0,
      "date_maj": "2025-11-13T11:16:39.834194"
    },
    {
      "symbole": "PRSC",
      "nom": "TRACTAFRIC MOTORS COTE D'IVOIRE",
      "dernier": 3975.0,
      "variation": -0.62,
      "ouverture": 4000.0,
      "haut": 3975.0,
      "bas": 3975.0,
      "volume": 754,
      "veille": 4000.0,
      "date_maj": "2025-11-13T11:16:39.834382"
    },
    {
      "symbole": "SAFC",
      "nom": "SAFCA COTE D'IVOIRE",
      "dernier": 2850.0,
      "variation": -1.72,
      "ouverture": 2850.0,
      "haut": 2850.0,
      "bas": 2850.0,
      "volume": 7255,
      "veille": 2900.0,
      "date_maj": "2025-11-13T11:16:39.834638"
    },
    {
      "symbole": "SCRC",
      "nom": "SUCRIVOIRE COTE D'IVOIRE",
      "dernier": 1050.0,
      "variation": -0.47,
      "ouverture": 1050.0,
      "haut": 1050.0,
      "bas": 1050.0,
      "volume": 5938,
      "veille": 1055.0,
      "date_maj": "2025-11-13T11:16:39.834868"
    },
    {
      "symbole": "SDCC",
      "nom": "SODE COTE D'IVOIRE",
      "dernier": 6000.0,
      "variation": -1.64,
      "ouverture": 6000.0,
      "haut": 6000.0,
      "bas": 6000.0,
      "volume": 46,
      "veille": 6100.0,
      "date_maj": "2025-11-13T11:16:39.835026"
    },
    {
      "symbole": "SDSC",
      "nom": "AFRICA GLOBAL LOGISTICS COTE D'IVOIRE",
      "dernier": 1460.0,
      "variation": 0.0,
      "ouverture": 1460.0,
      "haut": 1460.0,
      "bas": 1460.0,
      "volume": 58535,
      "veille": 1460.0,
      "date_maj": "2025-11-13T11:16:39.835207"
    },
    {
      "symbole": "SEMC",
      "nom": "EVIOSYS PACKAGING SIEM COTE D'IVOIRE",
      "dernier": 700.0,
      "variation": 0.0,
      "ouverture": 0.0,
      "haut": 700.0,
      "bas": 700.0,
      "volume": 0,
      "veille": 700.0,
      "date_maj": "2025-11-13T11:16:39.835362"
    },
    {
      "symbole": "SGBC",
      "nom": "SOCIETE GENERALE COTE D'IVOIRE",
      "dernier": 27000.0,
      "variation": -1.1,
      "ouverture": 28200.0,
      "haut": 27000.0,
      "bas": 27000.0,
      "volume": 638,
      "veille": 27200.0,
      "date_maj": "2025-11-13T11:16:39.835486"
    },
    {
      "symbole": "SHEC",
      "nom": "VIVO ENERGY COTE D'IVOIRE",
      "dernier": 1235.0,
      "variation": 0.0,
      "ouverture": 1230.0,
      "haut": 1235.0,
      "bas": 1235.0,
      "volume": 1927,
      "veille": 1235.0,
      "date_maj": "2025-11-13T11:16:39.835619"
    },
    {
      "symbole": "SIBC",
      "nom": "SOCIETE IVOIRIENNE DE BANQUE COTE D'IVOIRE",
      "dernier": 5700.0,
      "variation": 0.88,
      "ouverture": 5700.0,
      "haut": 5700.0,
      "bas": 5700.0,
      "volume": 596,
      "veille": 5650.0,
      "date_maj": "2025-11-13T11:16:39.835720"
    },
    {
      "symbole": "SICC",
      "nom": "SICOR COTE D'IVOIRE",
      "dernier": 3335.0,
      "variation": 0.0,
      "ouverture": 0.0,
      "haut": 3335.0,
      "bas": 3335.0,
      "volume": 0,
      "veille": 3335.0,
      "date_maj": "2025-11-13T11:16:39.835821"
    },
    {
      "symbole": "SIVC",
      "nom": "AIR LIQUIDE COTE D'IVOIRE",
      "dernier": 690.0,
      "variation": -1.43,
      "ouverture": 700.0,
      "haut": 690.0,
      "bas": 690.0,
      "volume": 20339,
      "veille": 700.0,
      "date_maj": "2025-11-13T11:16:39.835919"
    },
    {
      "symbole": "SLBC",
      "nom": "SOLIBRA COTE D'IVOIRE",
      "dernier": 24900.0,
      "variation": 0.0,
      "ouverture": 24500.0,
      "haut": 24900.0,
      "bas": 24900.0,
      "volume": 235,
      "veille": 24900.0,
      "date_maj": "2025-11-13T11:16:39.836005"
    },
    {
      "symbole": "SMBC",
      "nom": "SMB COTE D'IVOIRE",
      "dernier": 9850.0,
      "variation": 0.51,
      "ouverture": 9850.0,
      "haut": 9850.0,
      "bas": 9850.0,
      "volume": 1080,
      "veille": 9850.0,
      "date_maj": "2025-11-13T11:16:39.836099"
    },
    {
      "symbole": "SNTS",
      "nom": "SONATEL SENEGAL",
      "dernier": 25495.0,
      "variation": 0.16,
      "ouverture": 25500.0,
      "haut": 25495.0,
      "bas": 25495.0,
      "volume": 1245,
      "veille": 25500.0,
      "date_maj": "2025-11-13T11:16:39.836188"
    },
    {
      "symbole": "SOGC",
      "nom": "SOGB COTE D'IVOIRE",
      "dernier": 8000.0,
      "variation": -1.6,
      "ouverture": 7950.0,
      "haut": 8000.0,
      "bas": 8000.0,
      "volume": 14559,
      "veille": 8130.0,
      "date_maj": "2025-11-13T11:16:39.836349"
    },
    {
      "symbole": "SPHC",
      "nom": "SAPH COTE D'IVOIRE",
      "dernier": 7480.0,
      "variation": 0.0,
      "ouverture": 7480.0,
      "haut": 7480.0,
      "bas": 7480.0,
      "volume": 554,
      "veille": 7480.0,
      "date_maj": "2025-11-13T11:16:39.836507"
    },
    {
      "symbole": "STAC",
      "nom": "SETAO COTE D'IVOIRE",
      "dernier": 1195.0,
      "variation": 0.0,
      "ouverture": 1195.0,
      "haut": 1195.0,
      "bas": 1195.0,
      "volume": 168,
      "veille": 1195.0,
      "date_maj": "2025-11-13T11:16:39.836718"
    },
    {
      "symbole": "STBC",
      "nom": "SITAB COTE D'IVOIRE",
      "dernier": 19450.0,
      "variation": -0.31,
      "ouverture": 19600.0,
      "haut": 19450.0,
      "bas": 19450.0,
      "volume": 1578,
      "veille": 19510.0,
      "date_maj": "2025-11-13T11:16:39.836876"
    },
    {
      "symbole": "TTLC",
      "nom": "TOTALENERGIES MARKETING COTE D'IVOIRE",
      "dernier": 2300.0,
      "variation": 0.0,
      "ouverture": 2350.0,
      "haut": 2300.0,
      "bas": 2300.0,
      "volume": 749,
      "veille": 2300.0,
      "date_maj": "2025-11-13T11:16:39.836995"
    },
    {
      "symbole": "TTLS",
      "nom": "TOTALENERGIES MARKETING SENEGAL",
      "dernier": 2490.0,
      "variation": 0.2,
      "ouverture": 2490.0,
      "haut": 2490.0,
      "bas": 2490.0,
      "volume": 91,
      "veille": 2485.0,
      "date_maj": "2025-11-13T11:16:39.837086"
    },
    {
      "symbole": "UNLC",
      "nom": "UNILEVER COTE D'IVOIRE",
      "dernier": 28690.0,
      "variation": 0.0,
      "ouverture": 26700.0,
      "haut": 28690.0,
      "bas": 28690.0,
      "volume": 11,
      "veille": 28690.0,
      "date_maj": "2025-11-13T11:16:39.837240"
    },
    {
      "symbole": "UNXC",
      "nom": "UNIWAX COTE D'IVOIRE",
      "dernier": 1470.0,
      "variation": -0.68,
      "ouverture": 1370.0,
      "haut": 1470.0,
      "bas": 1470.0,
      "volume": 24131,
      "veille": 1470.0,
      "date_maj": "2025-11-13T11:16:39.837395"
    }
  ]
}