{
  "metadata": {
    "date_maj": "2025-10-23T11:28:53.029345",
    "timestamp": 1761218933,
    "nombre_actions": 47,
    "source": "BRVM",
    "version": "ultra_robuste",
    "statut": "succès",
    "environment": "github_actions"
  },
  "data": [
    {
      "symbole": "ABJC",
      "nom": "SERVAIR ABIDJAN COTE D'IVOIRE",
      "dernier": 2200.0,
      "variation": 0.0,
      "ouverture": 2200.0,
      "haut": 2200.0,
      "bas": 2200.0,
      "volume": 17684,
      "veille": 2200.0,
      "date_maj": "2025-10-23T11:28:53.021289"
    },
    {
      "symbole": "BICB",
      "nom": "BANQUE INTERNATIONALE POUR L’INDUSTRIE ET LE COMMERCE DU BENIN",
      "dernier": 5250.0,
      "variation": -0.19,
      "ouverture": 5260.0,
      "haut": 5250.0,
      "bas": 5250.0,
      "volume": 2719,
      "veille": 5260.0,
      "date_maj": "2025-10-23T11:28:53.021483"
    },
    {
      "symbole": "BICC",
      "nom": "BICI COTE D'IVOIRE",
      "dernier": 19200.0,
      "variation": -1.51,
      "ouverture": 19005.0,
      "haut": 19200.0,
      "bas": 19200.0,
      "volume": 1004,
      "veille": 19400.0,
      "date_maj": "2025-10-23T11:28:53.021652"
    },
    {
      "symbole": "BNBC",
      "nom": "BERNABE COTE D'IVOIRE",
      "dernier": 1820.0,
      "variation": 1.11,
      "ouverture": 1800.0,
      "haut": 1820.0,
      "bas": 1820.0,
      "volume": 897,
      "veille": 1800.0,
      "date_maj": "2025-10-23T11:28:53.021937"
    },
    {
      "symbole": "BOAB",
      "nom": "BANK OF AFRICA BENIN",
      "dernier": 5040.0,
      "variation": -1.18,
      "ouverture": 5100.0,
      "haut": 5040.0,
      "bas": 5040.0,
      "volume": 733,
      "veille": 5100.0,
      "date_maj": "2025-10-23T11:28:53.022152"
    },
    {
      "symbole": "BOABF",
      "nom": "BANK OF AFRICA BURKINA FASO",
      "dernier": 3785.0,
      "variation": -0.39,
      "ouverture": 3800.0,
      "haut": 3785.0,
      "bas": 3785.0,
      "volume": 1569,
      "veille": 3800.0,
      "date_maj": "2025-10-23T11:28:53.022328"
    },
    {
      "symbole": "BOAC",
      "nom": "BANK OF AFRICA COTE D'IVOIRE",
      "dernier": 7280.0,
      "variation": -0.14,
      "ouverture": 7290.0,
      "haut": 7280.0,
      "bas": 7280.0,
      "volume": 1800,
      "veille": 7290.0,
      "date_maj": "2025-10-23T11:28:53.022509"
    },
    {
      "symbole": "BOAM",
      "nom": "BANK OF AFRICA MALI",
      "dernier": 4300.0,
      "variation": 1.18,
      "ouverture": 4250.0,
      "haut": 4300.0,
      "bas": 4300.0,
      "volume": 2918,
      "veille": 4250.0,
      "date_maj": "2025-10-23T11:28:53.022716"
    },
    {
      "symbole": "BOAN",
      "nom": "BANK OF AFRICA NIGER",
      "dernier": 2570.0,
      "variation": 0.0,
      "ouverture": 2570.0,
      "haut": 2570.0,
      "bas": 2570.0,
      "volume": 105,
      "veille": 2570.0,
      "date_maj": "2025-10-23T11:28:53.022901"
    },
    {
      "symbole": "BOAS",
      "nom": "BANK OF AFRICA SENEGAL",
      "dernier": 5500.0,
      "variation": -1.79,
      "ouverture": 5550.0,
      "haut": 5500.0,
      "bas": 5500.0,
      "volume": 6735,
      "veille": 5600.0,
      "date_maj": "2025-10-23T11:28:53.023083"
    },
    {
      "symbole": "CABC",
      "nom": "SICABLE COTE D'IVOIRE",
      "dernier": 1700.0,
      "variation": -0.58,
      "ouverture": 1745.0,
      "haut": 1700.0,
      "bas": 1700.0,
      "volume": 602,
      "veille": 1710.0,
      "date_maj": "2025-10-23T11:28:53.023359"
    },
    {
      "symbole": "CBIBF",
      "nom": "CORIS BANK INTERNATIONAL BURKINA FASO",
      "dernier": 9975.0,
      "variation": -0.05,
      "ouverture": 9980.0,
      "haut": 9975.0,
      "bas": 9975.0,
      "volume": 69,
      "veille": 9980.0,
      "date_maj": "2025-10-23T11:28:53.023535"
    },
    {
      "symbole": "CFAC",
      "nom": "CFAO MOTORS COTE D'IVOIRE",
      "dernier": 1745.0,
      "variation": -0.85,
      "ouverture": 1780.0,
      "haut": 1745.0,
      "bas": 1745.0,
      "volume": 3109,
      "veille": 1760.0,
      "date_maj": "2025-10-23T11:28:53.023777"
    },
    {
      "symbole": "CIEC",
      "nom": "CIE COTE D'IVOIRE",
      "dernier": 2450.0,
      "variation": -1.61,
      "ouverture": 2495.0,
      "haut": 2450.0,
      "bas": 2450.0,
      "volume": 1296,
      "veille": 2490.0,
      "date_maj": "2025-10-23T11:28:53.023922"
    },
    {
      "symbole": "ECOC",
      "nom": "ECOBANK COTE D'IVOIRE",
      "dernier": 14190.0,
      "variation": 1.36,
      "ouverture": 14000.0,
      "haut": 14190.0,
      "bas": 14190.0,
      "volume": 176,
      "veille": 14000.0,
      "date_maj": "2025-10-23T11:28:53.024022"
    },
    {
      "symbole": "ETIT",
      "nom": "Ecobank Transnational Incorporated TOGO",
      "dernier": 22.0,
      "variation": 0.0,
      "ouverture": 21.0,
      "haut": 22.0,
      "bas": 22.0,
      "volume": 160121,
      "veille": 22.0,
      "date_maj": "2025-10-23T11:28:53.024183"
    },
    {
      "symbole": "FTSC",
      "nom": "FILTISAC COTE D'IVOIRE",
      "dernier": 2850.0,
      "variation": -0.18,
      "ouverture": 2800.0,
      "haut": 2850.0,
      "bas": 2850.0,
      "volume": 2815,
      "veille": 2855.0,
      "date_maj": "2025-10-23T11:28:53.024323"
    },
    {
      "symbole": "LNBB",
      "nom": "LOTERIE NATIONALE DU BENIN",
      "dernier": 3995.0,
      "variation": 0.0,
      "ouverture": 3860.0,
      "haut": 3995.0,
      "bas": 3995.0,
      "volume": 172,
      "veille": 3995.0,
      "date_maj": "2025-10-23T11:28:53.024478"
    },
    {
      "symbole": "NEIC",
      "nom": "NEI-CEDA COTE D'IVOIRE",
      "dernier": 690.0,
      "variation": 0.0,
      "ouverture": 690.0,
      "haut": 690.0,
      "bas": 690.0,
      "volume": 108,
      "veille": 690.0,
      "date_maj": "2025-10-23T11:28:53.024613"
    },
    {
      "symbole": "NSBC",
      "nom": "NSIA BANQUE COTE D'IVOIRE",
      "dernier": 11000.0,
      "variation": -0.9,
      "ouverture": 10995.0,
      "haut": 11000.0,
      "bas": 11000.0,
      "volume": 357,
      "veille": 11100.0,
      "date_maj": "2025-10-23T11:28:53.024735"
    },
    {
      "symbole": "NTLC",
      "nom": "NESTLE COTE D'IVOIRE",
      "dernier": 13300.0,
      "variation": -0.75,
      "ouverture": 13300.0,
      "haut": 13300.0,
      "bas": 13300.0,
      "volume": 437,
      "veille": 13400.0,
      "date_maj": "2025-10-23T11:28:53.024834"
    },
    {
      "symbole": "ONTBF",
      "nom": "ONATEL BURKINA FASO",
      "dernier": 2405.0,
      "variation": 0.0,
      "ouverture": 2405.0,
      "haut": 2405.0,
      "bas": 2405.0,
      "volume": 577,
      "veille": 2405.0,
      "date_maj": "2025-10-23T11:28:53.024924"
    },
    {
      "symbole": "ORAC",
      "nom": "ORANGE COTE D'IVOIRE",
      "dernier": 15000.0,
      "variation": 0.0,
      "ouverture": 15000.0,
      "haut": 15000.0,
      "bas": 15000.0,
      "volume": 230,
      "veille": 15000.0,
      "date_maj": "2025-10-23T11:28:53.025011"
    },
    {
      "symbole": "ORGT",
      "nom": "ORAGROUP TOGO",
      "dernier": 2600.0,
      "variation": 0.0,
      "ouverture": 2710.0,
      "haut": 2600.0,
      "bas": 2600.0,
      "volume": 21213,
      "veille": 2600.0,
      "date_maj": "2025-10-23T11:28:53.025172"
    },
    {
      "symbole": "PALC",
      "nom": "PALM COTE D'IVOIRE",
      "dernier": 8890.0,
      "variation": -0.06,
      "ouverture": 8895.0,
      "haut": 8890.0,
      "bas": 8890.0,
      "volume": 6591,
      "veille": 8895.0,
      "date_maj": "2025-10-23T11:28:53.025310"
    },
    {
      "symbole": "PRSC",
      "nom": "TRACTAFRIC MOTORS COTE D'IVOIRE",
      "dernier": 3995.0,
      "variation": 1.4,
      "ouverture": 3900.0,
      "haut": 3995.0,
      "bas": 3995.0,
      "volume": 305,
      "veille": 3940.0,
      "date_maj": "2025-10-23T11:28:53.025406"
    },
    {
      "symbole": "SAFC",
      "nom": "SAFCA COTE D'IVOIRE",
      "dernier": 2745.0,
      "variation": 1.86,
      "ouverture": 2695.0,
      "haut": 2745.0,
      "bas": 2745.0,
      "volume": 2014,
      "veille": 2695.0,
      "date_maj": "2025-10-23T11:28:53.025554"
    },
    {
      "symbole": "SCRC",
      "nom": "SUCRIVOIRE COTE D'IVOIRE",
      "dernier": 1255.0,
      "variation": -1.18,
      "ouverture": 1270.0,
      "haut": 1255.0,
      "bas": 1255.0,
      "volume": 952,
      "veille": 1270.0,
      "date_maj": "2025-10-23T11:28:53.025710"
    },
    {
      "symbole": "SDCC",
      "nom": "SODE COTE D'IVOIRE",
      "dernier": 6200.0,
      "variation": 0.08,
      "ouverture": 6200.0,
      "haut": 6200.0,
      "bas": 6200.0,
      "volume": 82,
      "veille": 6195.0,
      "date_maj": "2025-10-23T11:28:53.025816"
    },
    {
      "symbole": "SDSC",
      "nom": "AFRICA GLOBAL LOGISTICS COTE D'IVOIRE",
      "dernier": 1445.0,
      "variation": 0.35,
      "ouverture": 1490.0,
      "haut": 1445.0,
      "bas": 1445.0,
      "volume": 2509,
      "veille": 1440.0,
      "date_maj": "2025-10-23T11:28:53.025969"
    },
    {
      "symbole": "SEMC",
      "nom": "EVIOSYS PACKAGING SIEM COTE D'IVOIRE",
      "dernier": 700.0,
      "variation": 0.0,
      "ouverture": 0.0,
      "haut": 700.0,
      "bas": 700.0,
      "volume": 0,
      "veille": 700.0,
      "date_maj": "2025-10-23T11:28:53.026105"
    },
    {
      "symbole": "SGBC",
      "nom": "SOCIETE GENERALE COTE D'IVOIRE",
      "dernier": 27500.0,
      "variation": -0.72,
      "ouverture": 27700.0,
      "haut": 27500.0,
      "bas": 27500.0,
      "volume": 386,
      "veille": 27700.0,
      "date_maj": "2025-10-23T11:28:53.026200"
    },
    {
      "symbole": "SHEC",
      "nom": "VIVO ENERGY COTE D'IVOIRE",
      "dernier": 1240.0,
      "variation": 1.64,
      "ouverture": 1250.0,
      "haut": 1240.0,
      "bas": 1240.0,
      "volume": 3109,
      "veille": 1220.0,
      "date_maj": "2025-10-23T11:28:53.026348"
    },
    {
      "symbole": "SIBC",
      "nom": "SOCIETE IVOIRIENNE DE BANQUE COTE D'IVOIRE",
      "dernier": 5700.0,
      "variation": -0.87,
      "ouverture": 5600.0,
      "haut": 5700.0,
      "bas": 5700.0,
      "volume": 3288,
      "veille": 5750.0,
      "date_maj": "2025-10-23T11:28:53.026549"
    },
    {
      "symbole": "SICC",
      "nom": "SICOR COTE D'IVOIRE",
      "dernier": 3500.0,
      "variation": 0.0,
      "ouverture": 0.0,
      "haut": 3500.0,
      "bas": 3500.0,
      "volume": 0,
      "veille": 3500.0,
      "date_maj": "2025-10-23T11:28:53.026704"
    },
    {
      "symbole": "SIVC",
      "nom": "AIR LIQUIDE COTE D'IVOIRE",
      "dernier": 675.0,
      "variation": -0.74,
      "ouverture": 675.0,
      "haut": 675.0,
      "bas": 675.0,
      "volume": 1525,
      "veille": 680.0,
      "date_maj": "2025-10-23T11:28:53.026807"
    },
    {
      "symbole": "SLBC",
      "nom": "SOLIBRA COTE D'IVOIRE",
      "dernier": 18500.0,
      "variation": 0.0,
      "ouverture": 19300.0,
      "haut": 18500.0,
      "bas": 18500.0,
      "volume": 33,
      "veille": 18500.0,
      "date_maj": "2025-10-23T11:28:53.026965"
    },
    {
      "symbole": "SMBC",
      "nom": "SMB COTE D'IVOIRE",
      "dernier": 9600.0,
      "variation": 0.0,
      "ouverture": 9800.0,
      "haut": 9600.0,
      "bas": 9600.0,
      "volume": 814,
      "veille": 9600.0,
      "date_maj": "2025-10-23T11:28:53.027155"
    },
    {
      "symbole": "SNTS",
      "nom": "SONATEL SENEGAL",
      "dernier": 26650.0,
      "variation": 0.6,
      "ouverture": 26500.0,
      "haut": 26650.0,
      "bas": 26650.0,
      "volume": 1191,
      "veille": 26490.0,
      "date_maj": "2025-10-23T11:28:53.027290"
    },
    {
      "symbole": "SOGC",
      "nom": "SOGB COTE D'IVOIRE",
      "dernier": 8500.0,
      "variation": 0.0,
      "ouverture": 8500.0,
      "haut": 8500.0,
      "bas": 8500.0,
      "volume": 1307,
      "veille": 8500.0,
      "date_maj": "2025-10-23T11:28:53.027384"
    },
    {
      "symbole": "SPHC",
      "nom": "SAPH COTE D'IVOIRE",
      "dernier": 8050.0,
      "variation": 0.62,
      "ouverture": 8000.0,
      "haut": 8050.0,
      "bas": 8050.0,
      "volume": 1482,
      "veille": 8000.0,
      "date_maj": "2025-10-23T11:28:53.027471"
    },
    {
      "symbole": "STAC",
      "nom": "SETAO COTE D'IVOIRE",
      "dernier": 1180.0,
      "variation": 0.0,
      "ouverture": 1200.0,
      "haut": 1180.0,
      "bas": 1180.0,
      "volume": 146,
      "veille": 1180.0,
      "date_maj": "2025-10-23T11:28:53.027558"
    },
    {
      "symbole": "STBC",
      "nom": "SITAB COTE D'IVOIRE",
      "dernier": 19500.0,
      "variation": 1.43,
      "ouverture": 19795.0,
      "haut": 19500.0,
      "bas": 19500.0,
      "volume": 1016,
      "veille": 19225.0,
      "date_maj": "2025-10-23T11:28:53.027736"
    },
    {
      "symbole": "TTLC",
      "nom": "TOTALENERGIES MARKETING COTE D'IVOIRE",
      "dernier": 2345.0,
      "variation": -0.21,
      "ouverture": 2400.0,
      "haut": 2345.0,
      "bas": 2345.0,
      "volume": 4821,
      "veille": 2345.0,
      "date_maj": "2025-10-23T11:28:53.027872"
    },
    {
      "symbole": "TTLS",
      "nom": "TOTALENERGIES MARKETING SENEGAL",
      "dernier": 2500.0,
      "variation": -1.96,
      "ouverture": 2550.0,
      "haut": 2500.0,
      "bas": 2500.0,
      "volume": 1333,
      "veille": 2550.0,
      "date_maj": "2025-10-23T11:28:53.027967"
    },
    {
      "symbole": "UNLC",
      "nom": "UNILEVER COTE D'IVOIRE",
      "dernier": 18605.0,
      "variation": 0.0,
      "ouverture": 0.0,
      "haut": 18605.0,
      "bas": 18605.0,
      "volume": 0,
      "veille": 18605.0,
      "date_maj": "2025-10-23T11:28:53.028055"
    },
    {
      "symbole": "UNXC",
      "nom": "UNIWAX COTE D'IVOIRE",
      "dernier": 1840.0,
      "variation": -2.65,
      "ouverture": 1890.0,
      "haut": 1840.0,
      "bas": 1840.0,
      "volume": 2124,
      "veille": 1875.0,
      "date_maj": "2025-10-23T11:28:53.028142"
    }
  ]
}